{
 "issues": [
  {
   "key": "SOCV-201",
   "fields": {
    "summary": "EVT1 HW power/DVFS 최적화 — U 발열의 HW 개선 판단",
    "issuetype": {
     "name": "발열"
    },
    "labels": [
     "project_v"
    ],
    "description": "EVT1 마감이 다가오는데 U 발열의 근본원인 분석이 미완이라, 수정이 실제 얼마나 개선할지 예측 신뢰도가 낮다 — 잘못 고치면 마감만 밀린다.",
    "priority": {
     "name": "High"
    },
    "status": {
     "name": "Closed"
    },
    "updated": "2026-01-26",
    "duedate": "2026-01-26"
   }
  },
  {
   "key": "SOCV-9052",
   "fields": {
    "summary": "[근거 요청] MFC/MFD 병렬 처리 model",
    "issuetype": {
     "name": "전력"
    },
    "labels": [
     "project_v"
    ],
    "description": "Confluence 확보 필요 — MFC/MFD 병렬 처리 model",
    "priority": {
     "name": "Medium"
    },
    "status": {
     "name": "Open"
    },
    "updated": "2026-01-26",
    "duedate": "2026-02-02"
   }
  },
  {
   "key": "SOCV-9053",
   "fields": {
    "summary": "[근거 요청] APV 표준화·고객 채택 전망 조사",
    "issuetype": {
     "name": "성능"
    },
    "labels": [
     "project_v"
    ],
    "description": "Confluence 확보 필요 — APV 표준화·고객 채택 전망 조사",
    "priority": {
     "name": "Medium"
    },
    "status": {
     "name": "Open"
    },
    "updated": "2026-01-26",
    "duedate": "2026-02-02"
   }
  },
  {
   "key": "SOCV-208",
   "fields": {
    "summary": "Multi-camera sensor mode seamless 전환 SW 선개발",
    "issuetype": {
     "name": "결함"
    },
    "labels": [
     "project_v"
    ],
    "description": "전환 지연 실측과 zoom 사용 패턴 데이터가 없어 재구조화 범위(어느 배율 구간까지 seamless로 만들지)를 정하지 못하고 있다.",
    "priority": {
     "name": "Medium"
    },
    "customfield_lesson": "Multi-camera sensor mode seamless 전환 SW 선개발 — 대응 경과를 차기 과제 검토에 반영",
    "status": {
     "name": "Resolved"
    },
    "updated": "2026-01-26",
    "duedate": "2026-01-26"
   }
  },
  {
   "key": "SOCW-9022",
   "fields": {
    "summary": "[근거 요청] 미반영 시 영향 정량화",
    "issuetype": {
     "name": "성능"
    },
    "labels": [
     "project_w"
    ],
    "description": "Dashboard 확보 필요 — 미반영 시 영향 정량화",
    "priority": {
     "name": "Medium"
    },
    "status": {
     "name": "Resolved"
    },
    "updated": "2026-01-26",
    "duedate": "2026-01-26"
   }
  },
  {
   "key": "SOCW-307",
   "fields": {
    "summary": "Camera pipeline area 최적화 — 수익성(ISP)",
    "issuetype": {
     "name": "아키검토"
    },
    "labels": [
     "project_w"
    ],
    "description": "area-perf model 정확도와 축소 시 IQ/perf 영향 데이터가 미확보 — 블록 공유(재사용)안의 확신은 근거 없이 과대평가된 상태다.",
    "status": {
     "name": "Resolved"
    },
    "updated": "2026-01-26",
    "duedate": "2026-01-26"
   }
  }
 ]
}